mdctn/__init__.py
mdctn/core/__init__.py
mdctn/core/imdct.py
mdctn/core/mdct.py
mdctn/imdct.py
mdctn/mdct.py
mdctn-0.3.1.dist-info/WHEEL
mdctn-0.3.1.dist-info/METADATA
mdctn-0.3.1.dist-info/RECORD
