Metadata-Version: 2.1
Name: mdctn
Version: 0.3.1
Summary: Multidimensional Modified Discrete Cosine Transforms
Home-page: https://github.com/zeroby0/mdctn.git
License: MIT
Keywords: MDCT,DCT,FFT,lapped,signal-processing,lapped-orthogonal-transform
Author: Aravind Reddy Voggu
Author-email: aravind.reddy@iiitb.org
Maintainer: Aravind Reddy Voggu
Maintainer-email: aravind.reddy@iiitb.org
Requires-Python: >=3.8,<4.0
Classifier: License :: OSI Approved :: MIT License
Classifier: Programming Language :: Python :: 3
Classifier: Programming Language :: Python :: 3.8
Classifier: Programming Language :: Python :: 3.9
Classifier: Programming Language :: Python :: 3.10
Classifier: Programming Language :: Python :: 3.11
Requires-Dist: numpy (>=1.23.5,<2.0.0)
Requires-Dist: scipy (>=1.9.3,<2.0.0)
Project-URL: Repository, https://github.com/zeroby0/mdctn.git
